Metadata-Version: 2.1
Name: itmfinder
Version: 0.1.1
Summary: Intratumoral Microbiome Finder Tool
Home-page: https://github.com/DongqiangZeng0808/itmfinder
Author: Dongqiang Zeng
Author-email: interlaken@smu.edu.cn
License: MIT License
Classifier: Development Status :: 3 - Alpha
Classifier: Intended Audience :: Science/Research
Classifier: Topic :: Scientific/Engineering :: Bio-Informatics
Classifier: License :: OSI Approved :: MIT License
Classifier: Programming Language :: Python :: 3
Classifier: Programming Language :: Python :: 3.6
Classifier: Programming Language :: Python :: 3.7
Classifier: Programming Language :: Python :: 3.8
Classifier: Programming Language :: Python :: 3.9
Requires-Python: >=3.6
Requires-Dist: numpy
Requires-Dist: pandas
Requires-Dist: biopython
Requires-Dist: matplotlib
Requires-Dist: scikit-learn
